colours_library
