Metadata-Version: 1.0
Name: colours-library
Version: 0.13.1
Summary: Colours library package
Home-page: https://gitlab.bitcomp.intra/eryk_malczyk/colours_library.git
Author: ErykM
Author-email: eryk.malczyk@bitcomp.fi
License: some_license
Platform: UNKNOWN
